{"type":"Sprite","props":{"texture":"test/images/car.png","presetID":1,"pivotY":45,"pivotX":19.5,"name":"levelTxt","isPresetRoot":true,"group":1,"gravityScale":0.5},"compId":1,"child":[{"type":"Script","props":{"width":39,"presetID":2,"height":90,"runtime":"Laya.BoxCollider"},"compId":2},{"type":"Script","props":{"type":"dynamic","presetID":3,"group":-1,"gravityScale":0,"bullet":false,"runtime":"Laya.RigidBody"},"compId":3},{"type":"Script","props":{"presetID":7,"runtime":"script/Car.ts"},"compId":8}],"loadList":["test/images/car.png"],"loadList3D":[]}